{
  "id": "SNOWSHINE",
  "slug": "snowshine",
  "skills": {
    "normalAttack": {
      "name": "失温猛击",
      "type": "普通攻击",
      "type_key": "normalAttack",
      "level_headers": [
        "1",
        "2",
        "3",
        "4",
        "5",
        "6",
        "7",
        "8",
        "9",
        "M1",
        "M2",
        "M3"
      ],
      "row_labels": [
        "普攻第一段倍率",
        "普攻第二段倍率",
        "普攻第三段倍率",
        "处决攻击倍率",
        "下落攻击倍率"
      ],
      "levels": {
        "1": {
          "rows": {
            "普攻第一段倍率": "55%",
            "普攻第二段倍率": "59%",
            "普攻第三段倍率": "100%",
            "处决攻击倍率": "400%",
            "下落攻击倍率": "80%"
          }
        },
        "2": {
          "rows": {
            "普攻第一段倍率": "61%",
            "普攻第二段倍率": "64%",
            "普攻第三段倍率": "110%",
            "处决攻击倍率": "440%",
            "下落攻击倍率": "88%"
          }
        },
        "3": {
          "rows": {
            "普攻第一段倍率": "66%",
            "普攻第二段倍率": "70%",
            "普攻第三段倍率": "120%",
            "处决攻击倍率": "480%",
            "下落攻击倍率": "96%"
          }
        },
        "4": {
          "rows": {
            "普攻第一段倍率": "72%",
            "普攻第二段倍率": "76%",
            "普攻第三段倍率": "130%",
            "处决攻击倍率": "520%",
            "下落攻击倍率": "104%"
          }
        },
        "5": {
          "rows": {
            "普攻第一段倍率": "77%",
            "普攻第二段倍率": "82%",
            "普攻第三段倍率": "140%",
            "处决攻击倍率": "560%",
            "下落攻击倍率": "112%"
          }
        },
        "6": {
          "rows": {
            "普攻第一段倍率": "83%",
            "普攻第二段倍率": "88%",
            "普攻第三段倍率": "150%",
            "处决攻击倍率": "600%",
            "下落攻击倍率": "120%"
          }
        },
        "7": {
          "rows": {
            "普攻第一段倍率": "88%",
            "普攻第二段倍率": "94%",
            "普攻第三段倍率": "160%",
            "处决攻击倍率": "640%",
            "下落攻击倍率": "128%"
          }
        },
        "8": {
          "rows": {
            "普攻第一段倍率": "94%",
            "普攻第二段倍率": "99%",
            "普攻第三段倍率": "170%",
            "处决攻击倍率": "680%",
            "下落攻击倍率": "136%"
          }
        },
        "9": {
          "rows": {
            "普攻第一段倍率": "99%",
            "普攻第二段倍率": "105%",
            "普攻第三段倍率": "180%",
            "处决攻击倍率": "720%",
            "下落攻击倍率": "144%"
          }
        },
        "M1": {
          "rows": {
            "普攻第一段倍率": "106%",
            "普攻第二段倍率": "113%",
            "普攻第三段倍率": "193%",
            "处决攻击倍率": "770%",
            "下落攻击倍率": "154%"
          }
        },
        "M2": {
          "rows": {
            "普攻第一段倍率": "114%",
            "普攻第二段倍率": "121%",
            "普攻第三段倍率": "208%",
            "处决攻击倍率": "830%",
            "下落攻击倍率": "166%"
          }
        },
        "M3": {
          "rows": {
            "普攻第一段倍率": "124%",
            "普攻第二段倍率": "132%",
            "普攻第三段倍率": "225%",
            "处决攻击倍率": "900%",
            "下落攻击倍率": "180%"
          }
        }
      }
    },
    "skill": {
      "name": "饱和性防御",
      "type": "战技",
      "type_key": "skill",
      "level_headers": [
        "1",
        "2",
        "3",
        "4",
        "5",
        "6",
        "7",
        "8",
        "9",
        "M1",
        "M2",
        "M3"
      ],
      "row_labels": [
        "伤害倍率",
        "失衡值",
        "庇护效果",
        "返还技力"
      ],
      "levels": {
        "1": {
          "rows": {
            "伤害倍率": "200%",
            "失衡值": "20",
            "庇护效果": "90%",
            "返还技力": "30"
          }
        },
        "2": {
          "rows": {
            "伤害倍率": "220%",
            "失衡值": "20",
            "庇护效果": "90%",
            "返还技力": "30"
          }
        },
        "3": {
          "rows": {
            "伤害倍率": "240%",
            "失衡值": "20",
            "庇护效果": "90%",
            "返还技力": "30"
          }
        },
        "4": {
          "rows": {
            "伤害倍率": "260%",
            "失衡值": "20",
            "庇护效果": "90%",
            "返还技力": "30"
          }
        },
        "5": {
          "rows": {
            "伤害倍率": "280%",
            "失衡值": "20",
            "庇护效果": "90%",
            "返还技力": "30"
          }
        },
        "6": {
          "rows": {
            "伤害倍率": "300%",
            "失衡值": "20",
            "庇护效果": "90%",
            "返还技力": "30"
          }
        },
        "7": {
          "rows": {
            "伤害倍率": "320%",
            "失衡值": "20",
            "庇护效果": "90%",
            "返还技力": "30"
          }
        },
        "8": {
          "rows": {
            "伤害倍率": "340%",
            "失衡值": "20",
            "庇护效果": "90%",
            "返还技力": "30"
          }
        },
        "9": {
          "rows": {
            "伤害倍率": "360%",
            "失衡值": "20",
            "庇护效果": "90%",
            "返还技力": "30"
          }
        },
        "M1": {
          "rows": {
            "伤害倍率": "385%",
            "失衡值": "20",
            "庇护效果": "90%",
            "返还技力": "30"
          }
        },
        "M2": {
          "rows": {
            "伤害倍率": "415%",
            "失衡值": "20",
            "庇护效果": "90%",
            "返还技力": "30"
          }
        },
        "M3": {
          "rows": {
            "伤害倍率": "450%",
            "失衡值": "20",
            "庇护效果": "90%",
            "返还技力": "30"
          }
        }
      }
    },
    "link": {
      "name": "极地救援",
      "type": "连携技",
      "type_key": "link",
      "level_headers": [
        "1",
        "2",
        "3",
        "4",
        "5",
        "6",
        "7",
        "8",
        "9",
        "M1",
        "M2",
        "M3"
      ],
      "row_labels": [
        "冷却时间",
        "初始治疗基础值",
        "每点意志增加的初始治疗值",
        "持续治疗基础值",
        "每点意志增加的持续治疗值",
        "持续治疗间隔（秒）",
        "持续时间（秒）"
      ],
      "levels": {
        "1": {
          "rows": {
            "冷却时间": "25s",
            "初始治疗基础值": "96",
            "每点意志增加的初始治疗值": "0.22",
            "持续治疗基础值": "24",
            "每点意志增加的持续治疗值": "0.06",
            "持续治疗间隔（秒）": "0.5",
            "持续时间（秒）": "3"
          }
        },
        "2": {
          "rows": {
            "冷却时间": "25s",
            "初始治疗基础值": "115",
            "每点意志增加的初始治疗值": "0.27",
            "持续治疗基础值": "29",
            "每点意志增加的持续治疗值": "0.07",
            "持续治疗间隔（秒）": "0.5",
            "持续时间（秒）": "3"
          }
        },
        "3": {
          "rows": {
            "冷却时间": "25s",
            "初始治疗基础值": "134",
            "每点意志增加的初始治疗值": "0.31",
            "持续治疗基础值": "34",
            "每点意志增加的持续治疗值": "0.08",
            "持续治疗间隔（秒）": "0.5",
            "持续时间（秒）": "3"
          }
        },
        "4": {
          "rows": {
            "冷却时间": "25s",
            "初始治疗基础值": "154",
            "每点意志增加的初始治疗值": "0.36",
            "持续治疗基础值": "38",
            "每点意志增加的持续治疗值": "0.09",
            "持续治疗间隔（秒）": "0.5",
            "持续时间（秒）": "3"
          }
        },
        "5": {
          "rows": {
            "冷却时间": "25s",
            "初始治疗基础值": "163",
            "每点意志增加的初始治疗值": "0.38",
            "持续治疗基础值": "41",
            "每点意志增加的持续治疗值": "0.1",
            "持续治疗间隔（秒）": "0.5",
            "持续时间（秒）": "3"
          }
        },
        "6": {
          "rows": {
            "冷却时间": "25s",
            "初始治疗基础值": "173",
            "每点意志增加的初始治疗值": "0.4",
            "持续治疗基础值": "43",
            "每点意志增加的持续治疗值": "0.1",
            "持续治疗间隔（秒）": "0.5",
            "持续时间（秒）": "3"
          }
        },
        "7": {
          "rows": {
            "冷却时间": "25s",
            "初始治疗基础值": "182",
            "每点意志增加的初始治疗值": "0.43",
            "持续治疗基础值": "46",
            "每点意志增加的持续治疗值": "0.11",
            "持续治疗间隔（秒）": "0.5",
            "持续时间（秒）": "3"
          }
        },
        "8": {
          "rows": {
            "冷却时间": "25s",
            "初始治疗基础值": "192",
            "每点意志增加的初始治疗值": "0.45",
            "持续治疗基础值": "48",
            "每点意志增加的持续治疗值": "0.11",
            "持续治疗间隔（秒）": "0.5",
            "持续时间（秒）": "3"
          }
        },
        "9": {
          "rows": {
            "冷却时间": "24s",
            "初始治疗基础值": "202",
            "每点意志增加的初始治疗值": "0.47",
            "持续治疗基础值": "50",
            "每点意志增加的持续治疗值": "0.12",
            "持续治疗间隔（秒）": "0.5",
            "持续时间（秒）": "3"
          }
        },
        "M1": {
          "rows": {
            "冷却时间": "24s",
            "初始治疗基础值": "206",
            "每点意志增加的初始治疗值": "0.48",
            "持续治疗基础值": "52",
            "每点意志增加的持续治疗值": "0.12",
            "持续治疗间隔（秒）": "0.5",
            "持续时间（秒）": "3"
          }
        },
        "M2": {
          "rows": {
            "冷却时间": "24s",
            "初始治疗基础值": "211",
            "每点意志增加的初始治疗值": "0.49",
            "持续治疗基础值": "53",
            "每点意志增加的持续治疗值": "0.12",
            "持续治疗间隔（秒）": "0.5",
            "持续时间（秒）": "3"
          }
        },
        "M3": {
          "rows": {
            "冷却时间": "23s",
            "初始治疗基础值": "216",
            "每点意志增加的初始治疗值": "0.5",
            "持续治疗基础值": "54",
            "每点意志增加的持续治疗值": "0.13",
            "持续治疗间隔（秒）": "0.5",
            "持续时间（秒）": "3"
          }
        }
      }
    },
    "ultimate": {
      "name": "凛冽寒霜",
      "type": "终结技",
      "type_key": "ultimate",
      "level_headers": [
        "1",
        "2",
        "3",
        "4",
        "5",
        "6",
        "7",
        "8",
        "9",
        "M1",
        "M2",
        "M3"
      ],
      "row_labels": [
        "所需终结技能量",
        "爆炸伤害倍率",
        "失衡值",
        "持续伤害倍率",
        "持续伤害间隔（秒）",
        "持续时间（秒）"
      ],
      "levels": {
        "1": {
          "rows": {
            "所需终结技能量": "80",
            "爆炸伤害倍率": "200%",
            "失衡值": "15",
            "持续伤害倍率": "29%",
            "持续伤害间隔（秒）": "0.5",
            "持续时间（秒）": "5"
          }
        },
        "2": {
          "rows": {
            "所需终结技能量": "80",
            "爆炸伤害倍率": "220%",
            "失衡值": "15",
            "持续伤害倍率": "32%",
            "持续伤害间隔（秒）": "0.5",
            "持续时间（秒）": "5"
          }
        },
        "3": {
          "rows": {
            "所需终结技能量": "80",
            "爆炸伤害倍率": "240%",
            "失衡值": "15",
            "持续伤害倍率": "35%",
            "持续伤害间隔（秒）": "0.5",
            "持续时间（秒）": "5"
          }
        },
        "4": {
          "rows": {
            "所需终结技能量": "80",
            "爆炸伤害倍率": "260%",
            "失衡值": "15",
            "持续伤害倍率": "37%",
            "持续伤害间隔（秒）": "0.5",
            "持续时间（秒）": "5"
          }
        },
        "5": {
          "rows": {
            "所需终结技能量": "80",
            "爆炸伤害倍率": "280%",
            "失衡值": "15",
            "持续伤害倍率": "40%",
            "持续伤害间隔（秒）": "0.5",
            "持续时间（秒）": "5"
          }
        },
        "6": {
          "rows": {
            "所需终结技能量": "80",
            "爆炸伤害倍率": "300%",
            "失衡值": "15",
            "持续伤害倍率": "43%",
            "持续伤害间隔（秒）": "0.5",
            "持续时间（秒）": "5"
          }
        },
        "7": {
          "rows": {
            "所需终结技能量": "80",
            "爆炸伤害倍率": "320%",
            "失衡值": "15",
            "持续伤害倍率": "46%",
            "持续伤害间隔（秒）": "0.5",
            "持续时间（秒）": "5"
          }
        },
        "8": {
          "rows": {
            "所需终结技能量": "80",
            "爆炸伤害倍率": "340%",
            "失衡值": "15",
            "持续伤害倍率": "49%",
            "持续伤害间隔（秒）": "0.5",
            "持续时间（秒）": "5"
          }
        },
        "9": {
          "rows": {
            "所需终结技能量": "80",
            "爆炸伤害倍率": "360%",
            "失衡值": "15",
            "持续伤害倍率": "52%",
            "持续伤害间隔（秒）": "0.5",
            "持续时间（秒）": "5"
          }
        },
        "M1": {
          "rows": {
            "所需终结技能量": "80",
            "爆炸伤害倍率": "385%",
            "失衡值": "20",
            "持续伤害倍率": "55%",
            "持续伤害间隔（秒）": "0.5",
            "持续时间（秒）": "5"
          }
        },
        "M2": {
          "rows": {
            "所需终结技能量": "80",
            "爆炸伤害倍率": "415%",
            "失衡值": "20",
            "持续伤害倍率": "60%",
            "持续伤害间隔（秒）": "0.5",
            "持续时间（秒）": "5"
          }
        },
        "M3": {
          "rows": {
            "所需终结技能量": "80",
            "爆炸伤害倍率": "450%",
            "失衡值": "20",
            "持续伤害倍率": "65%",
            "持续伤害间隔（秒）": "0.5",
            "持续时间（秒）": "5"
          }
        }
      }
    }
  },
  "_skill_count": 4,
  "source": {
    "url": "https://warfarin.wiki/cn/operators/snowshine",
    "fetched_at": "2026-03-26T02:47:29.036Z",
    "parser_version": "1.0.0",
    "extracted_at": "2026-03-26T03:39:19.200Z"
  }
}